azcp_wrapper/__init__.py
azcp_wrapper/azcp_client.py
azcp_wrapper/azcp_summary.py
azcp_wrapper/azcp_utils.py
azcp_wrapper/logging_config.py
azcp_wrapper/setup.py
azcp_wrapper/utils/__init__.py
azcp_wrapper/utils/constants.py
azcp_wrapper/utils/execute_command.py
azcp_wrapper-0.0.20.dist-info/LICENSE
azcp_wrapper-0.0.20.dist-info/METADATA
azcp_wrapper-0.0.20.dist-info/WHEEL
azcp_wrapper-0.0.20.dist-info/entry_points.txt
azcp_wrapper-0.0.20.dist-info/top_level.txt
azcp_wrapper-0.0.20.dist-info/RECORD
